biobb_flexserv/__init__.py
biobb_flexserv/py.typed
biobb_flexserv/flexserv/__init__.py
biobb_flexserv/flexserv/bd_run.py
biobb_flexserv/flexserv/dmd_run.py
biobb_flexserv/flexserv/nma_run.py
biobb_flexserv/pcasuite/__init__.py
biobb_flexserv/pcasuite/pcz_animate.py
biobb_flexserv/pcasuite/pcz_bfactor.py
biobb_flexserv/pcasuite/pcz_collectivity.py
biobb_flexserv/pcasuite/pcz_evecs.py
biobb_flexserv/pcasuite/pcz_hinges.py
biobb_flexserv/pcasuite/pcz_info.py
biobb_flexserv/pcasuite/pcz_lindemann.py
biobb_flexserv/pcasuite/pcz_similarity.py
biobb_flexserv/pcasuite/pcz_stiffness.py
biobb_flexserv/pcasuite/pcz_unzip.py
biobb_flexserv/pcasuite/pcz_zip.py
biobb_flexserv-5.2.0.dist-info/licenses/LICENSE
biobb_flexserv-5.2.0.dist-info/METADATA
biobb_flexserv-5.2.0.dist-info/WHEEL
biobb_flexserv-5.2.0.dist-info/entry_points.txt
biobb_flexserv-5.2.0.dist-info/top_level.txt
biobb_flexserv-5.2.0.dist-info/RECORD
